<?xml version="1.0" ?>
<odoo noupdate="1">
    <record id="efact_storage" model="storage.backend">
        <field name="name">e.Fact Storage</field>
        <field name="backend_type">sftp</field>
        <field name="sftp_server">efact.eacat.cat</field>
        <field name="sftp_port">22</field>
        <field name="sftp_login">usuario</field>
        <field name="sftp_password">password</field>
    </record>
    <record id="efact_backend" model="edi.backend">
        <field name="name">e.Fact</field>
        <field name="backend_type_id" ref="l10n_es_facturae.facturae_backend_type" />
        <field name="storage_id" ref="efact_storage" />
        <field name="output_dir_pending">in</field>
        <field name="input_dir_pending">statout</field>
    </record>
    <record id="facturae_efact_update_exchange_type" model="edi.exchange.type">
        <field name="name">Update Facturae e.Fact</field>
        <field name="code">l10n_es_facturae_efact_update</field>
        <field name="backend_type_id" ref="l10n_es_facturae.facturae_backend_type" />
        <field name="backend_id" ref="efact_backend" />
        <field name="direction">input</field>
        <field name="exchange_filename_pattern">{record_name}-{dt}</field>
        <field name="exchange_file_ext">xml</field>
    </record>
    <record id="update_efact_job" model="ir.cron">
        <field name="name">eFACT update Job</field>
        <field name="active">True</field>
        <field name="user_id" ref="base.user_root" />
        <field name="priority">8</field>
        <field name="interval_type">hours</field>
        <field name="state">code</field>
        <field name="numbercall">-1</field>
        <field name="model_id" ref="edi.model_edi_exchange_record" />
        <field name="code">model.efact_check_history()</field>
    </record>
</odoo>
